MANIFEST.in
README.md
license.txt
requirements.txt
setup.py
django_deploy/__init__.py
django_deploy/models.py
django_deploy/project.py
django_deploy/system.py
django_deploy/utils.py
django_deploy/views.py
django_deploy.egg-info/PKG-INFO
django_deploy.egg-info/SOURCES.txt
django_deploy.egg-info/dependency_links.txt
django_deploy.egg-info/requires.txt
django_deploy.egg-info/top_level.txt
django_deploy/management/__init__.py
django_deploy/management/commands/__init__.py
django_deploy/management/commands/deploy_project.py
django_deploy/management/commands/redeploy_project.py
django_deploy/management/commands/setup_geodjango.py
django_deploy/management/commands/setup_project.py
django_deploy/management/commands/setup_server.py
django_deploy/management/commands/tester.py
django_deploy/scripts/create_template_postgis-1.5.sh
django_deploy/templates/apache.conf
django_deploy/templates/wsgi.py