Metadata-Version: 1.0
Name: django-deploy
Version: 0.1.0
Summary: Django deployment utility
Home-page: http://github.com/johnthedebs/django-deploy
Author: John Debs
Author-email: johnthedebs@gmail.com
License: UNKNOWN
Platform: UNKNOWN
Classifier: Development Status :: 3 - Alpha
Classifier: Environment :: Web Environment
Classifier: Framework :: Django
Classifier: Intended Audience :: Developers
Classifier: License :: OSI Approved :: MIT License
Classifier: Programming Language :: Python
